hypern-0.3.15.dist-info/METADATA
hypern-0.3.15.dist-info/WHEEL
hypern-0.3.15.dist-info/licenses/LICENSE
hypern/hypern.pyi
hypern/cli/__init__.py
hypern/cli/commands.py
hypern/enum.py
hypern/routing/endpoint.py
hypern/routing/queue.py
hypern/routing/__init__.py
hypern/routing/route.py
hypern/routing/parser.py
hypern/routing/dispatcher.py
hypern/args_parser.py
hypern/i18n/__init__.py
hypern/worker.py
hypern/reload.py
hypern/application.py
hypern/logging/__init__.py
hypern/logging/logger.py
hypern/py.typed
hypern/caching/backend.py
hypern/caching/redis_backend.py
hypern/caching/strategies.py
hypern/caching/__init__.py
hypern/config.py
hypern/processpool.py
hypern/__init__.py
hypern/exceptions/http.py
hypern/exceptions/base.py
hypern/exceptions/errors.py
hypern/exceptions/__init__.py
hypern/exceptions/common.py
hypern/exceptions/formatters.py
hypern/datastructures.py
hypern/middleware/compress.py
hypern/middleware/base.py
hypern/middleware/cors.py
hypern/middleware/i18n.py
hypern/middleware/limit.py
hypern/middleware/cache.py
hypern/middleware/__init__.py
hypern/middleware/security.py
hypern/database/sqlx/field.py
hypern/database/sqlx/model.py
hypern/database/sqlx/query.py
hypern/database/sqlx/__init__.py
hypern/database/sqlx/migrate.py
hypern/database/sqlalchemy/repository.py
hypern/database/sqlalchemy/config.py
hypern/database/sqlalchemy/__init__.py
hypern/database/__init__.py
hypern/auth/decorators.py
hypern/auth/middleware.py
hypern/auth/jwt.py
hypern/auth/__init__.py
hypern/auth/providers.py
hypern/openapi/swagger.py
hypern/openapi/__init__.py
hypern/openapi/schemas.py
hypern/ws/heartbeat.py
hypern/ws/channel.py
hypern/ws/__init__.py
hypern/ws/room.py
hypern/ws/route.py
hypern/gateway/gateway.py
hypern/gateway/proxy.py
hypern/gateway/aggregator.py
hypern/gateway/service.py
hypern/gateway/__init__.py
hypern/response/response.py
hypern/response/__init__.py
hypern/hypern.cpython-310-aarch64-linux-gnu.so
hypern-0.3.15.dist-info/RECORD
