Metadata-Version: 2.4
Name: hypern
Version: 0.3.15
Classifier: Programming Language :: Rust
Classifier: Programming Language :: Python :: Implementation :: CPython
Classifier: Programming Language :: Python :: Implementation :: PyPy
Requires-Dist: sqlalchemy[asyncio]==2.0.31
Requires-Dist: pyjwt==2.8.0
Requires-Dist: pydash==8.0.3
Requires-Dist: sentry-sdk==2.11.0
Requires-Dist: celery==5.4.0
Requires-Dist: psycopg==3.2.3
Requires-Dist: pyyaml==6.0.2
Requires-Dist: orjson==3.10.11
Requires-Dist: multiprocess==0.70.17
Requires-Dist: uvloop==0.21.0 ; platform_machine != 'armv7l' and platform_python_implementation == 'CPython' and sys_platform != 'win32'
Requires-Dist: watchdog==6.0.0
Requires-Dist: psutil==6.1.0
Requires-Dist: msgpack==1.1.0
Requires-Dist: redis==5.2.1
Requires-Dist: pydantic==2.10.4
License-File: LICENSE
Summary: A Fast Async Python backend with a Rust runtime.
Author-email: Martin Dang <vannghiem848@gmail.com>
Requires-Python: >=3.10
